brnet/__init__.py
brnet/brnet.py
brnet-0.0.6.dist-info/LICENSE
brnet-0.0.6.dist-info/METADATA
brnet-0.0.6.dist-info/WHEEL
brnet-0.0.6.dist-info/entry_points.txt
brnet-0.0.6.dist-info/top_level.txt
brnet-0.0.6.dist-info/RECORD
