Metadata-Version: 2.1
Name: brnet
Version: 0.0.6
Summary: Tool to convert ethernet interface to bridge for emulation
License: MIT License
Project-URL: Source, https://github.com/athornton/brnet
Keywords: brnet,pi,emulation
Classifier: Development Status :: 4 - Beta
Classifier: License :: OSI Approved :: MIT License
Classifier: Programming Language :: Python
Classifier: Programming Language :: Python :: 3
Classifier: Programming Language :: Python :: 3.9
Classifier: Programming Language :: Python :: 3.10
Classifier: Programming Language :: Python :: 3.11
Classifier: Intended Audience :: Developers
Classifier: Natural Language :: English
Classifier: Operating System :: POSIX
Classifier: Typing :: Typed
Requires-Python: >=3.9
License-File: LICENSE
